Peertable-0.1.3.6.dist-info/METADATA
Peertable-0.1.3.6.dist-info/RECORD
Peertable-0.1.3.6.dist-info/WHEEL
Peertable-0.1.3.6.dist-info/top_level.txt
peertable/__init__.py
peertable/__main__.py
