Metadata-Version: 2.1
Name: Peertable
Version: 0.1.3.6
Summary: A peer-to-peer network infrastructure library.
Home-page: UNKNOWN
Author: Gustavo6046
Author-email: gugurehermann@gmail.com
License: MIT
Keywords: p2p peer-to-peer peer network infrastructure library
Platform: UNKNOWN
